.coveragerc
LICENSE
MANIFEST.in
NOTICE
README
conftest.py
dynpool.py
setup.py
tox.ini
docs/Makefile
docs/api.rst
docs/conf.py
docs/index.rst
docs/install.rst
dynpool.egg-info/PKG-INFO
dynpool.egg-info/SOURCES.txt
dynpool.egg-info/dependency_links.txt
dynpool.egg-info/top_level.txt
test/test_dynpool.py